galaxy/net/__init__.py
galaxy/net/auth.py
galaxy/net/compression.py
galaxy/net/constant.py
galaxy/net/endpoint.py
galaxy/net/fix/__init__.py
galaxy/net/fix/fix.py
galaxy/net/ftp/__init__.py
galaxy/net/ftp/ftp.py
galaxy/net/http/__init__.py
galaxy/net/http/http.py
galaxy/net/http/request.py
galaxy/net/http/response.py
galaxy/net/http/session.py
galaxy/net/imap/__init__.py
galaxy/net/imap/imap.py
galaxy/net/monitor.py
galaxy/net/net.py
galaxy/net/parser.py
galaxy/net/pop3/__init__.py
galaxy/net/pop3/pop3.py
galaxy/net/request.py
galaxy/net/response.py
galaxy/net/scp/__init__.py
galaxy/net/scp/scp.py
galaxy/net/session.py
galaxy/net/sftp/__init__.py
galaxy/net/sftp/sftp.py
galaxy/net/smb/__init__.py
galaxy/net/smb/smb.py
galaxy/net/smtp/__init__.py
galaxy/net/smtp/smtp.py
galaxy/net/snmp/__init__.py
galaxy/net/snmp/snmp.py
galaxy/net/soap/__init__.py
galaxy/net/soap/response.py
galaxy/net/soap/soap.py
galaxy/net/soap/transport.py
galaxy/net/socket.py
galaxy/net/ssh/__init__.py
galaxy/net/ssh/protocol.py
galaxy/net/ssh/session.py
galaxy/net/ssh/ssh.py
galaxy/net/ssh/transport.py
galaxy/net/tcp/__init__.py
galaxy/net/tcp/tcp.py
galaxy/net/uri.py
galaxy/net/ws/__init__.py
galaxy/net/ws/ws.py
galaxy/net/zmq/__init__.py
galaxy/net/zmq/protocol.py
galaxy/net/zmq/zmq.py
galaxy_py_net-0.0.7.dist-info/AUTHORS
galaxy_py_net-0.0.7.dist-info/COPYING.md
galaxy_py_net-0.0.7.dist-info/LICENSE.txt
galaxy_py_net-0.0.7.dist-info/METADATA
galaxy_py_net-0.0.7.dist-info/WHEEL
galaxy_py_net-0.0.7.dist-info/RECORD
