Metadata-Version: 2.3
Name: galaxy-py-net
Version: 0.0.7
Summary: Python Network for the Galaxy Project
License: Apache-2.0
Keywords: galaxy,galaxy-net
Author: Bastien Saltel
Author-email: bastien.saltel@gmail.com
Maintainer: Bastien Saltel
Maintainer-email: bastien.saltel@gmail.com
Requires-Python: >=3.10,<4.0
Classifier: Development Status :: 3 - Alpha
Classifier: Programming Language :: Python :: 3
Classifier: Operating System :: OS Independent
Requires-Dist: aioftp
Requires-Dist: aiohttp
Requires-Dist: aioimaplib
Requires-Dist: aiosmb
Requires-Dist: aiosmtpd
Requires-Dist: aiosmtplib
Requires-Dist: aiozmq
Requires-Dist: asyncssh
Requires-Dist: galaxy-py-data
Requires-Dist: galaxy-py-error
Requires-Dist: galaxy-py-kernel
Requires-Dist: galaxy-py-perfo
Requires-Dist: galaxy-py-service
Requires-Dist: galaxy-py-utils
Requires-Dist: httpx
Requires-Dist: httpx_ntlm
Requires-Dist: ipykernel
Requires-Dist: ipython
Requires-Dist: jupyter_client
Requires-Dist: paramiko
Requires-Dist: puresnmp
Requires-Dist: pysftp
Requires-Dist: pysmb
Requires-Dist: pysnmp
Requires-Dist: pyzmq
Requires-Dist: quickfix
Requires-Dist: requests
Requires-Dist: requests_ntlm
Requires-Dist: scp
Requires-Dist: smbprotocol
Requires-Dist: tenacity
Requires-Dist: tornado
Requires-Dist: transitions
Requires-Dist: urllib3
Requires-Dist: websockets
Requires-Dist: zeep
Project-URL: Changelog, https://github.com/bsaltel/galaxy-py-net/blob/main/CHANGELOG.md
Project-URL: Documentation, https://github.com/bsaltel/galaxy-py-net
Project-URL: Homepage, https://github.com/bsaltel/galaxy-py-net
Project-URL: Issues, https://github.com/bsaltel/galaxy-py-net/issues
Project-URL: Repository, https://github.com/bsaltel/galaxy-py-net.git
